geopagos/__init__.py
geopagos/sdk.py
geopagos/client/__init__.py
geopagos/client/client.py
geopagos/schemas/__init__.py
geopagos/schemas/order.py
geopagos/schemas/payment.py
geopagos-0.0.2.dist-info/LICENCE
geopagos-0.0.2.dist-info/METADATA
geopagos-0.0.2.dist-info/WHEEL
geopagos-0.0.2.dist-info/top_level.txt
geopagos-0.0.2.dist-info/RECORD
