Metadata-Version: 2.1
Name: geopagos
Version: 0.0.2
Summary: Unoffial geopagos sdk to work with apps like (Viumi, Getnet, OpenPay, Taca Taca, Toque, Sipago...).
Author-email: Alvez Gerardo <alvezpope@gmail.com>
Project-URL: Homepage, https://github.com/alvezgr/unofficial-gp-sdk/
Project-URL: Issues, https://github.com/Alvezgr/unofficial-gp-sdk/issues
Classifier: Programming Language :: Python :: 3
Classifier: License :: OSI Approved :: MIT License
Classifier: Operating System :: OS Independent
Requires-Python: >=3.8
License-File: LICENCE
